sphinxawesome/__init__.py
sphinxawesome/sampdirective/__init__.py
sphinxawesome_sampdirective-1.0.5.dist-info/LICENSE
sphinxawesome_sampdirective-1.0.5.dist-info/WHEEL
sphinxawesome_sampdirective-1.0.5.dist-info/METADATA
sphinxawesome_sampdirective-1.0.5.dist-info/RECORD
