Metadata-Version: 2.1
Name: sphinxawesome-sampdirective
Version: 1.0.5
Summary: A Sphinx directive for literal blocks with emphasis
Home-page: https://github.com/kai687/sphinxawesome-sampdirective
License: MIT
Author: Kai Welke
Author-email: kai687@pm.me
Requires-Python: >=3.6.1,<4.0.0
Classifier: Framework :: Sphinx
Classifier: Framework :: Sphinx :: Extension
Classifier: License :: OSI Approved :: MIT License
Classifier: Programming Language :: Python
Classifier: Programming Language :: Python :: 3
Classifier: Programming Language :: Python :: 3.7
Classifier: Programming Language :: Python :: 3.8
Classifier: Topic :: Documentation
Classifier: Topic :: Documentation :: Sphinx
Classifier: Topic :: Software Development :: Documentation
Requires-Dist: importlib_metadata (>=1.6.1,<3.0.0); python_version < "3.8"
Requires-Dist: sphinx (>=2.2)
Project-URL: Repository, https://github.com/kai687/sphinxawesome-sampdirective
